Metadata-Version: 2.1
Name: numeros-primos-Jorge-2021
Version: 1.0
Summary: Calcula una secuencia de numeros primos
Home-page: UNKNOWN
Author: Jorge Fuertes
Author-email: jorgefuert94@outlook.es
License: GNU GPLv3
Keywords: pyoperaciones mathematical operations prime numbers
Platform: UNKNOWN
Classifier: Development Status :: 4 - Beta
Classifier: Intended Audience :: Developers
Classifier: Topic :: Utilities
Classifier: License :: OSI Approved :: GNU Lesser General Public License v3 (LGPLv3)
Classifier: Programming Language :: Python :: 3
Classifier: Operating System :: OS Independent
License-File: LICENSE
